sopel_501c3/__init__.py
sopel_501c3/config.py
sopel_501c3/db.py
sopel_501c3/plugin.py
sopel_501c3/types.py
sopel_501c3/util.py
sopel_501c3-0.1.0.dist-info/COPYING
sopel_501c3-0.1.0.dist-info/METADATA
sopel_501c3-0.1.0.dist-info/WHEEL
sopel_501c3-0.1.0.dist-info/entry_points.txt
sopel_501c3-0.1.0.dist-info/top_level.txt
sopel_501c3-0.1.0.dist-info/RECORD
