Metadata-Version: 2.2
Name: sopel-501c3
Version: 0.1.0
Summary: 501(c)(3) nonprofit lookup plugin for Sopel IRC bots. Based on Publication 78 data.
Author-email: dgw <dgw@technobabbl.es>
License: EFL-2.0
Project-URL: Homepage, https://github.com/dgw/sopel-501c3
Project-URL: Bug Tracker, https://github.com/dgw/sopel-501c3/issues
Keywords: sopel,plugin,bot,irc
Platform: Linux x86, x86-64
Classifier: Intended Audience :: Developers
Classifier: Intended Audience :: System Administrators
Classifier: License :: Eiffel Forum License (EFL)
Classifier: License :: OSI Approved :: Eiffel Forum License
Classifier: Topic :: Communications :: Chat :: Internet Relay Chat
Requires-Python: <4,>=3.8
License-File: COPYING
Requires-Dist: sopel>=8.0
Requires-Dist: sqlalchemy
